[
  {
    "住院流水号": "19050500000129",
    "ICD10编码": "C50.900",
    "诊断编号": "",
    "诊断时间": "2019-04-17 13:55:15.313000",
    "诊断名称": "乳房恶性肿瘤",
    "诊断类型": "",
    "院内诊断编码": "30016363"
  },
  {
    "住院流水号": "19050500000129",
    "ICD10编码": "E11.900",
    "诊断编号": "2.00",
    "诊断时间": "2019-05-05 00:00:00",
    "诊断名称": "2型糖尿病",
    "诊断类型": "入院诊断(补充)",
    "院内诊断编码": "30018693"
  },
  {
    "住院流水号": "19050500000129",
    "ICD10编码": "I10.x00x002",
    "诊断编号": "1.00",
    "诊断时间": "2019-05-05 00:00:00",
    "诊断名称": "高血压",
    "诊断类型": "入院诊断(补充)",
    "院内诊断编码": "30021788"
  },
  {
    "住院流水号": "19050500000129",
    "ICD10编码": "C50.900",
    "诊断编号": "1.00",
    "诊断时间": "2019-05-05 00:00:00",
    "诊断名称": "乳房恶性肿瘤",
    "诊断类型": "入院诊断",
    "院内诊断编码": "30016360"
  },
  {
    "住院流水号": "19050500000129",
    "ICD10编码": "C50.900",
    "诊断编号": "1.00",
    "诊断时间": "2019-05-05 00:00:00",
    "诊断名称": "乳房恶性肿瘤",
    "诊断类型": "目前诊断",
    "院内诊断编码": "30016360"
  },
  {
    "住院流水号": "19050500000129",
    "ICD10编码": "E11.900",
    "诊断编号": "2.00",
    "诊断时间": "2019-05-07 00:00:00",
    "诊断名称": "2型糖尿病",
    "诊断类型": "出院诊断(补充)",
    "院内诊断编码": "30018693"
  },
  {
    "住院流水号": "19050500000129",
    "ICD10编码": "I10.x00x002",
    "诊断编号": "1.00",
    "诊断时间": "2019-05-07 00:00:00",
    "诊断名称": "高血压",
    "诊断类型": "出院诊断(补充)",
    "院内诊断编码": "30021788"
  },
  {
    "住院流水号": "19050500000129",
    "ICD10编码": "C50.900",
    "诊断编号": "1.00",
    "诊断时间": "2019-05-07 00:00:00",
    "诊断名称": "乳房恶性肿瘤",
    "诊断类型": "出院诊断",
    "院内诊断编码": "30016360"
  }
]