[
  {
    "住院流水号": "21011700000152",
    "检查ID": "2021011920002330|1",
    "检查类型": "超声",
    "检查部位": "彩色超声",
    "检查子类型": "彩色超声",
    "图像所见": "双侧颈部、双侧锁骨上、双侧腋窝、双侧腹股沟未见明显异常肿大淋巴结。",
    "图像分析": "双侧颈部、双侧锁骨上、双侧腋窝、双侧腹股沟未见明显异常肿大淋巴结",
    "检查描述": "颈部、锁骨上、腋下、腹股沟淋巴结 彩色超声",
    "申请时间": "2021-01-17 11:47:58",
    "检查时间": "2021-01-19 15:10:28",
    "报告时间": "2021-01-19 15:56:24"
  },
  {
    "住院流水号": "21011700000152",
    "检查ID": "2021011700000300|1",
    "检查类型": "放射",
    "检查部位": "增强",
    "检查子类型": "血液科及日间病房专用",
    "图像所见": "双侧甲状腺大小、形态、密度未见明显异常，双侧基本对称。\n气管形态正常。其它颈部软组织无明显异常。双侧颈部血管旁多发淋巴结显示。\n两肺透亮度增高，两肺斑片索条及细网格状影；局部胸膜增厚。\n两肺门区未见异常密度影。\n胸膜未见增厚改变。\n主动脉，肺动脉主干及其左右分支内造影剂密度均匀。\n各大血管边界清晰。\n纵隔内未见异常密度影。\nPICC置入术后。",
    "图像分析": "1、双侧颈部血管旁多发淋巴结显示。\n2、两肺肺气肿伴炎症，局部胸膜增厚，较2020-6-5大致相仿；\n请结合临床及其它相关检查，随诊。",
    "检查描述": "颈部+胸 增强",
    "申请时间": "2021-01-17 11:47:58",
    "检查时间": "2021-01-19 15:00:44",
    "报告时间": "2021-01-20 10:39:39"
  },
  {
    "住院流水号": "21011700000152",
    "检查ID": "2021011700000299|1",
    "检查类型": "放射",
    "检查部位": "增强",
    "检查子类型": "血液科及日间病房专用",
    "图像所见": "肝脏形态大小正常，肝内散在类圆形低密度影，无强化，较大者位于肝左叶，长径约1.5cm，肝右后叶结节样持续强化影。\n胆囊未见明显异常。\n脾脏形态大小正常，未见异常密度影。\n胰腺形态大小正常，未见异常密度影。\n两肾内见散在小类圆形低密度影，未见明显强化；左肾下极后方包膜毛糙。\nimg100腹膜后见小斑片影，范围约6×8mm。\n未见阳性结石影。\n膀胱形态正常，膀胱壁光整，未见异常密度。\n阑尾增粗。\n前列腺增大，其内见小斑片状高密度影。\n腹膜后未见异常增大的淋巴结影。",
    "图像分析": "肝、两肾多发囊性灶，肝右后叶血管瘤；两肾囊肿；前列腺增大伴钙化；阑尾增粗。请结合临床及其他检查，随访。",
    "检查描述": "腹+盆 增强",
    "申请时间": "2021-01-17 11:47:58",
    "检查时间": "2021-01-19 15:01:12",
    "报告时间": "2021-01-20 17:08:05"
  }
]