[
  {
    "护理记录名": "住院患者VTE",
    "时间": "2020-10-30 10:05:14",
    "内容": "外科住院患者院内VTE预防的推荐意见 VTE评分 0分，VTE发生风险： 非常低危； 一般出血风险人群，无需预防。"
  },
  {
    "护理记录名": "住院病案首页2012版",
    "时间": "2020-11-03 10:30:10",
    "内容": {
      "BAZL": "甲",
      "ZKRQ": "2020-11-03 10:27:32",
      "ZKYS": "00000000012086",
      "ZKHS": "00000000021604",
      "ZRHS": "00000000021604",
      "JXYS": "",
      "JXYSNEW": "",
      "SXYS": "",
      "BMY": "",
      "CYSJ": "2020-11-03 10:27:42",
      "CYKB": "甲状腺血管外科病区",
      "SJZYTS": "4",
      "XM": "||患者姓名||",
      "XB": "女",
      "CSRQ": "1964-08-14 00:00:00",
      "NL": "56岁",
      "GJ": "A156",
      "NL_YE": "",
      "XSECSTZ": "",
      "XSERYTZ": "",
      "CSD_S": "TM出生地__省TM",
      "CSD_SHI": "TM出生地__市TM",
      "CSD_X": "",
      "JG_S": "TM出生地__省TM",
      "JG_SHI": "",
      "MZ": "汉族",
      "SFZH": "310108196408144849",
      "HY": "已婚",
      "ZY": "退(离)休人员                                                ",
      "XZZ": "TM现住址详细文本TM",
      "DH_XZZ": "TM手机号TM",
      "YB_XZZ": "200333",
      "YB_HKDZ": "310000",
      "HKDZ": "TM户口地址详细文本TM",
      "DWJDZ": "TM单位地址TM",
      "DH_DWJDZ": "13361956413",
      "YB_DWJDZ": "200333",
      "LXRXM": "TM联系人姓名TM",
      "GX": "",
      "DZ_LXR": "",
      "DH_LXR": "TM联系人手机号TM",
      "RYTJ": "门诊",
      "QZRQ": "2020-10-31 08:49:30",
      "MJZZDID": "30018573",
      "ZYCS": "1",
      "RYSJ": "2020-10-30 08:49:30",
      "RYKB": "甲状腺血管外科病区",
      "MJZZDLTBZ": "1",
      "BLH": "F2020-11711/11712",
      "YWGM": "无",
      "GMYW": "",
      "SWHZSJ": "/",
      "KZR": "00000000011073",
      "ZRYS": "00000000010284",
      "ZZYS": "00000000010925",
      "ZYYS": "00000000012086",
      "LYFS": "医嘱离院",
      "NJSJG": "",
      "ZZYJH31": "无",
      "ZZYMD": "",
      "T_RYQ": "/",
      "S_RYQ": "/",
      "F_RYQ": "/",
      "T_RYH": "/",
      "S_RYH": "/",
      "F_RYH": "/",
      "ZKKB": "",
      "JBBM_MJZ": "E04.101",
      "MJZZD": "甲状腺结节",
      "XX": "未查",
      "RH": "未查",
      "SXFY": "/",
      "QJCS": "0",
      "CGCS": "0",
      "YXSE": "False",
      "XSEHKDZ": "",
      "XSEFM": "",
      "XSEYQMDSC": "",
      "XSETC": "",
      "XSECC": "",
      "XSEDTJST": "",
      "XSECHCXL": "",
      "CYYYSL": "",
      "CYZYSL": "",
      "RYYYSL": "",
      "RYZYSL": "",
      "BLZD": "双甲乳头状微癌",
      "BRRYBQ": "3",
      "病人信息": {
        "姓名": "||患者姓名||",
        "性别": "女",
        "科室": "甲状腺血管外科病区",
        "床号": "+545床",
        "住院号": "z209856",
        "住院流水号": "20103000000070",
        "年龄": "56",
        "出生年月": "1964-08-14",
        "入院时间": "1900-01-01",
        "出院时间": ""
      },
      "zd": {
        "row": [
          {
            "lx": "主要诊断",
            "jbbm": "C73.x00",
            "jbmc": "甲状腺恶性肿瘤",
            "rybq": "临床未确定",
            "cyqk": "治愈",
            "id4zd": "30016532",
            "ltbz4zd": "1",
            "blzdbm": "",
            "blzdmc": "",
            "blzdid": "",
            "blzdltbz": ""
          },
          {
            "lx": "其他诊断",
            "jbbm": "无",
            "jbmc": "",
            "rybq": "",
            "cyqk": "",
            "id4zd": "",
            "ltbz4zd": "",
            "blzdbm": "",
            "blzdmc": "",
            "blzdid": "",
            "blzdltbz": ""
          }
        ]
      },
      "sszd": "",
      "ccqk": "",
      "yeqk": "",
      "ssxx": {
        "row": [
          {
            "sfdm": "",
            "sfmc": "",
            "sskssj": "2020-11-2 10:30:00",
            "mzfsdm": "",
            "ssysxm": "TM员工名称TM",
            "ssdh": "330763711672229888",
            "ssdm": "",
            "icd9cm3": "40.4000",
            "ssjssj": "2020-11-2 12:30:00",
            "ssys": "",
            "sszs1": "",
            "sszs2": "",
            "mzys": "",
            "sszs1xm": "TM手术助手姓名1TM",
            "sszs2xm": "TM手术助手姓名2TM",
            "mzfsmc": "",
            "mzysmc": "TM员工名称TM  ",
            "ssmc": "根治性颈淋巴结清扫",
            "sfid": "",
            "smbz": "jl",
            "cj": "",
            "ssdlsh": "3307637116722298881",
            "ssxh": "0",
            "qkxh": "1",
            "ssjb": "3",
            "sqks": "4120700",
            "asa": "",
            "sszs1lb": "",
            "sszs2lb": "",
            "ssyslb": "",
            "mzyslb": ""
          },
          {
            "sfdm": "",
            "sfmc": "",
            "sskssj": "2020-11-2 10:30:00",
            "mzfsdm": "",
            "ssysxm": "TM员工名称TM",
            "ssdh": "330763711672229888",
            "ssdm": "",
            "icd9cm3": "06.4x00",
            "ssjssj": "2020-11-2 12:30:00",
            "ssys": "",
            "sszs1": "",
            "sszs2": "",
            "mzys": "",
            "sszs1xm": "TM手术助手姓名1TM",
            "sszs2xm": "TM手术助手姓名2TM",
            "mzfsmc": "",
            "mzysmc": "TM员工名称TM  ",
            "ssmc": "甲状腺全部切除术",
            "sfid": "",
            "smbz": "jl",
            "cj": "",
            "ssdlsh": "3307637116722298882",
            "ssxh": "0",
            "qkxh": "1",
            "ssjb": "3",
            "sqks": "4120700",
            "asa": "",
            "sszs1lb": "",
            "sszs2lb": "",
            "ssyslb": "",
            "mzyslb": ""
          }
        ]
      }
    }
  },
  {
    "护理记录名": "恶性肿瘤报告卡",
    "时间": "2020-11-03 10:30:48",
    "内容": {
      "死亡补发病": "False",
      "诊断依据不详": "False",
      "尸检有病理": "False",
      "病理原发": "True",
      "病理继发": "False",
      "临床": "True",
      "CT": "False",
      "内窥镜": "False",
      "超声波": "False",
      "X线": "False",
      "尸检": "False",
      "手术": "False",
      "免疫": "False",
      "生化": "False",
      "血片": "False",
      "细胞学": "False",
      "原诊断日期": "",
      "原诊断": "",
      "死亡原因": "",
      "死亡日期": "",
      "报告日期": "2020-11-03 10:30:18",
      "报告医师": "00000000012592",
      "报告单位": "瑞金医院甲状腺血管外科病区",
      "首次诊断日期": "2020-10-30 08:49:30",
      "无法判定": "True",
      "四期": "False",
      "三期": "False",
      "二期": "False",
      "一期": "False",
      "确诊时期别M": "/",
      "确诊时期别N": "/",
      "确诊时期别T": "/",
      "病理号": "F2020-11711/11712",
      "病理学类型": "乳头状微癌",
      "诊断": "甲状腺",
      "实际居住地址": "TM实际居住地址详细文本TM",
      "实际居住地址街道": "TM实际居住地址街道名TM",
      "实际居住地址区县": "TM实际居住地址区县名TM",
      "常住户口地址": "TM常住户口地址详细文本TM",
      "常住户口地址街道": "TM常住户口地址街道名TM",
      "常住户口地址区县": "TM常住户口地址区县名TM",
      "工作单位": "",
      "职业": "",
      "出生年月": "1964-08-14 00:00:00",
      "民族": "01",
      "性别": "女",
      "患者姓名": "||患者姓名||",
      "家庭电话": "13361956413          201126",
      "住院号": "z209856",
      "身份证号": "310108196408144849",
      "门诊号": "M02920169",
      "附加信息": "",
      "病情已告知病人": "是",
      "ICD0": "",
      "ICD编号": "",
      "编号": "",
      "区县": "",
      "病情知情同意随访": "",
      "诊断部位左": "False",
      "诊断部位右": "False",
      "诊断部位双": "True",
      "诊断部位不详": "False",
      "病人信息": {
        "姓名": "||患者姓名||",
        "性别": "女",
        "科室": "",
        "床号": "",
        "住院号": "z209856",
        "住院流水号": "20103000000070",
        "年龄": "0",
        "出生年月": "1900-01-01",
        "入院时间": "1900-01-01",
        "出院时间": ""
      }
    }
  },
  {
    "护理记录名": "出院小结(死亡小结)",
    "时间": "2020-11-04 00:00:00",
    "内容": {
      "基本信息": {
        "出院诊断": "甲状腺恶性肿瘤",
        "床号": "+545床",
        "科别": "甲状腺血管外科病区",
        "入院时间": "2020-10-30 08:41",
        "出院时间": "    -  -     :",
        "姓名": "||患者姓名||",
        "性别": "女",
        "年龄": "56",
        "住院号": "z209856",
        "入院诊断": "甲状腺结节"
      },
      "入院时简要病史": "患者体检 发现甲状腺肿物。病程中，未见增大 ，患者无 声音嘶哑，无 饮水呛咳，无 突眼，无 颈部疼痛 ，无 吞咽呼吸不适，无 怕热多汗，无 心慌手抖等不适。遂至瑞金医院就诊，查甲状腺B超示：左侧甲状腺中部背侧一个  低 回声结节，大小约4.3*5.6*4.1 mm，呈垂直位生长，形状欠规则，内部回声欠均匀，边缘不光整，边界尚清，内部未见 点状强回声，拟诊TI-RADS 4C类；右侧甲状腺内可见几个  低 回声结节，之一大小约5.9*2.5 mm，未 垂直位生长，内部未见 点状强回声，拟诊TI-RADS 3类；右侧甲状腺上极背侧可见一低回声，大小约5.0*6.7*4.5mm，呈垂直位生长，形状欠规则，内部回声欠均匀，边缘光整，边界尚清，内部未见明显点状强回声，拟诊TI-RADS 4C类；无 颈区淋巴结肿大；无 穿刺结果。建议手术治疗。现患者为行手术治疗，拟诊“甲状腺结节”收治入院。 自发病以来，患者神清，精神可，睡眠可，胃纳可，二便无殊，近期体重无明显变化。 ",
      "体检摘要": "神清，精神可，颈软，气管居中，颈静脉无充盈，颈动脉无异常搏动。双侧甲状腺未及 肿物，   未及 肿大淋巴结。",
      "生命体征": {
        "T": "37",
        "P": "80",
        "R": "20",
        "BP高": "131",
        "BP低": "70"
      },
      "住院期间医疗情况": "【生化】  钠 137mmol/L  钾 3.67mmol/L  氯 102mmol/L  二氧化碳 23.1mmol/L  钙 2.08mmol/L  磷 0.99mmol/L 【激素】  25羟基维生素D(25-OH-VitD) 50.50nmol/L  甲状旁腺激素(PTH) 67.1pg/mL 【免疫】  抗梅毒螺旋体抗体 0.05  梅毒螺旋体RPR 阴性(-)",
      "出院时情况": "患者恢复良好，无切口渗血。",
      "病程与治疗情况": "患者入院完善相关检查排除手术禁忌后于2020-11 -02 在全麻下行中央组颈淋巴结清扫；甲状腺全部切除术（双侧），标本送冰冻病理：双甲乳头状微癌。术后生命征平稳。予以常规补液对症支持治疗。现患者术后恢复可，予以出院。",
      "出院后用药建议": "1、注意休息，合理营养，低碘饮食，防止感染。 2、术后5-6日拆线，病房每周二、四、六上午9-10点提供拆线服务。术后10日出石蜡病理报告；石蜡病理结果可能与目前诊断不符，最终诊断以石蜡病理为准；  3、出院带药：优甲乐100片、钙尔奇1瓶、罗盖全6盒，遵医嘱服用。 4、一月后门诊随访复查甲状腺功能，调整用药。 5、定期外科门诊随访，如有切口疼痛、发热等不适，及时就诊。 6、如遇特殊情况，石蜡病理需进一步行基因检测或免疫组化，病理科可能要求再次缴费，敬请理解。",
      "病人信息": {
        "姓名": "||患者姓名||",
        "性别": "女",
        "科室": "甲状腺血管外科病区",
        "床号": "+545床",
        "住院号": "z209856",
        "住院流水号": "20103000000070",
        "年龄": "56",
        "出生年月": "1964-08-14",
        "入院时间": "1900-01-01",
        "出院时间": ""
      }
    }
  }
]