[
  {
    "住院流水号": "20103000000070",
    "检查ID": "2020103010000661|1",
    "检查类型": "放射",
    "检查部位": "骨盆",
    "检查子类型": "X-RAY",
    "图像所见": "右侧髋臼变浅，髋臼缘骨质增生硬化，股骨头形态欠规则，关节面欠光整，关节面下见不规则高密度影，其间见小囊状低密度灶，关节间隙变窄。\n左侧髋臼外上缘骨质增生。股骨头形态未见明显异常。关节面光整，关节间隙正常。\n关节囊及关节周围软组织未见异常。\n左侧骶髂关节面欠光整，关节面下骨质见不规则斑片状密度增高影，关节间隙局部狭窄。\n右侧骶髂关节面光整，关节间隙正常。\n余骨盆各骨骨质未见异常。",
    "图像分析": "右侧髋臼变浅，右侧股骨头缺血性坏死伴髋关节骨关节炎改变；左侧髋关节退行性改变；左侧骶髂关节炎改变；请结合临床、病史查体及其他检查，随访。",
    "检查描述": "骨盆 骨盆",
    "申请时间": "2020-10-30 08:22:36",
    "检查时间": "2020-10-30 08:39:07",
    "报告时间": "2020-10-30 09:03:26"
  }
]