[
  {
    "住院流水号": "19072300000058",
    "记录时间": "2019-07-23 09:46:00",
    "检测项": "脉搏",
    "单位": "次/分",
    "检测值": "80.000",
    "说明": ""
  },
  {
    "住院流水号": "19072300000058",
    "记录时间": "2019-07-23 09:46:00",
    "检测项": "体重",
    "单位": "kg",
    "检测值": "56.700",
    "说明": ""
  },
  {
    "住院流水号": "19072300000058",
    "记录时间": "2019-07-23 09:46:00",
    "检测项": "血压",
    "单位": "mmHg",
    "检测值": "166.000/96.000",
    "说明": ""
  },
  {
    "住院流水号": "19072300000058",
    "记录时间": "2019-07-23 09:46:00",
    "检测项": "身高",
    "单位": "cm",
    "检测值": "160.000",
    "说明": ""
  },
  {
    "住院流水号": "19072300000058",
    "记录时间": "2019-07-23 09:46:00",
    "检测项": "体温",
    "单位": "℃",
    "检测值": "37.400",
    "说明": "耳温测量仪；"
  },
  {
    "住院流水号": "19072300000058",
    "记录时间": "2019-07-23 13:50:00",
    "检测项": "大便",
    "单位": "次",
    "检测值": "1.000",
    "说明": ""
  },
  {
    "住院流水号": "19072300000058",
    "记录时间": "2019-07-23 13:50:00",
    "检测项": "呼吸",
    "单位": "次/分",
    "检测值": "16.000",
    "说明": ""
  },
  {
    "住院流水号": "19072300000058",
    "记录时间": "2019-07-23 13:50:00",
    "检测项": "脉搏",
    "单位": "次/分",
    "检测值": "70.000",
    "说明": ""
  },
  {
    "住院流水号": "19072300000058",
    "记录时间": "2019-07-23 13:50:00",
    "检测项": "体温",
    "单位": "℃",
    "检测值": "37.500",
    "说明": "耳温测量仪；"
  },
  {
    "住院流水号": "19072300000058",
    "记录时间": "2019-07-23 14:27:00",
    "检测项": "呼吸",
    "单位": "次/分",
    "检测值": "20.000",
    "说明": ""
  },
  {
    "住院流水号": "19072300000058",
    "记录时间": "2019-07-23 15:55:00",
    "检测项": "血压",
    "单位": "mmHg",
    "检测值": "129.000/87.000",
    "说明": ""
  },
  {
    "住院流水号": "19072300000058",
    "记录时间": "2019-07-23 18:11:00",
    "检测项": "脉搏",
    "单位": "次/分",
    "检测值": "76.000",
    "说明": ""
  },
  {
    "住院流水号": "19072300000058",
    "记录时间": "2019-07-23 18:11:00",
    "检测项": "体温",
    "单位": "℃",
    "检测值": "37.200",
    "说明": "耳温测量仪；"
  },
  {
    "住院流水号": "19072300000058",
    "记录时间": "2019-07-23 18:11:00",
    "检测项": "呼吸",
    "单位": "次/分",
    "检测值": "16.000",
    "说明": ""
  },
  {
    "住院流水号": "19072300000058",
    "记录时间": "2019-07-24 06:11:00",
    "检测项": "脉搏",
    "单位": "次/分",
    "检测值": "78.000",
    "说明": ""
  },
  {
    "住院流水号": "19072300000058",
    "记录时间": "2019-07-24 06:11:00",
    "检测项": "体温",
    "单位": "℃",
    "检测值": "36.400",
    "说明": "耳温测量仪；"
  },
  {
    "住院流水号": "19072300000058",
    "记录时间": "2019-07-24 06:11:00",
    "检测项": "呼吸",
    "单位": "次/分",
    "检测值": "16.000",
    "说明": ""
  },
  {
    "住院流水号": "19072300000058",
    "记录时间": "2019-07-24 08:27:00",
    "检测项": "血压",
    "单位": "mmHg",
    "检测值": "150.000/90.000",
    "说明": ""
  },
  {
    "住院流水号": "19072300000058",
    "记录时间": "2019-07-24 14:07:00",
    "检测项": "大便",
    "单位": "次",
    "检测值": "1.000",
    "说明": ""
  },
  {
    "住院流水号": "19072300000058",
    "记录时间": "2019-07-24 14:07:00",
    "检测项": "脉搏",
    "单位": "次/分",
    "检测值": "74.000",
    "说明": ""
  },
  {
    "住院流水号": "19072300000058",
    "记录时间": "2019-07-24 14:07:00",
    "检测项": "体温",
    "单位": "℃",
    "检测值": "36.800",
    "说明": "耳温测量仪；"
  },
  {
    "住院流水号": "19072300000058",
    "记录时间": "2019-07-24 14:07:00",
    "检测项": "呼吸",
    "单位": "次/分",
    "检测值": "18.000",
    "说明": ""
  },
  {
    "住院流水号": "19072300000058",
    "记录时间": "2019-07-24 17:40:00",
    "检测项": "呼吸",
    "单位": "次/分",
    "检测值": "19.000",
    "说明": ""
  },
  {
    "住院流水号": "19072300000058",
    "记录时间": "2019-07-24 17:40:00",
    "检测项": "脉搏",
    "单位": "次/分",
    "检测值": "74.000",
    "说明": ""
  },
  {
    "住院流水号": "19072300000058",
    "记录时间": "2019-07-24 17:40:00",
    "检测项": "体温",
    "单位": "℃",
    "检测值": "37.200",
    "说明": "口温；"
  },
  {
    "住院流水号": "19072300000058",
    "记录时间": "2019-07-25 06:24:00",
    "检测项": "血压",
    "单位": "mmHg",
    "检测值": "141.000/80.000",
    "说明": ""
  },
  {
    "住院流水号": "19072300000058",
    "记录时间": "2019-07-25 06:24:00",
    "检测项": "呼吸",
    "单位": "次/分",
    "检测值": "20.000",
    "说明": ""
  },
  {
    "住院流水号": "19072300000058",
    "记录时间": "2019-07-25 06:24:00",
    "检测项": "脉搏",
    "单位": "次/分",
    "检测值": "78.000",
    "说明": ""
  },
  {
    "住院流水号": "19072300000058",
    "记录时间": "2019-07-25 06:24:00",
    "检测项": "体温",
    "单位": "℃",
    "检测值": "37.000",
    "说明": "口温；"
  },
  {
    "住院流水号": "19072300000058",
    "记录时间": "2019-07-25 10:24:00",
    "检测项": "血压",
    "单位": "mmHg",
    "检测值": "165.000/59.000",
    "说明": ""
  },
  {
    "住院流水号": "19072300000058",
    "记录时间": "2019-07-25 10:32:00",
    "检测项": "血压",
    "单位": "mmHg",
    "检测值": "135.000/85.000",
    "说明": ""
  },
  {
    "住院流水号": "19072300000058",
    "记录时间": "2019-07-25 10:32:00",
    "检测项": "血压",
    "单位": "mmHg",
    "检测值": "150.000/90.000",
    "说明": ""
  },
  {
    "住院流水号": "19072300000058",
    "记录时间": "2019-07-25 14:13:00",
    "检测项": "大便",
    "单位": "次",
    "检测值": "1.000",
    "说明": ""
  },
  {
    "住院流水号": "19072300000058",
    "记录时间": "2019-07-25 14:13:00",
    "检测项": "体温",
    "单位": "℃",
    "检测值": "36.900",
    "说明": "耳温测量仪；"
  },
  {
    "住院流水号": "19072300000058",
    "记录时间": "2019-07-25 14:13:00",
    "检测项": "脉搏",
    "单位": "次/分",
    "检测值": "76.000",
    "说明": ""
  },
  {
    "住院流水号": "19072300000058",
    "记录时间": "2019-07-25 14:13:00",
    "检测项": "血压",
    "单位": "mmHg",
    "检测值": "111.000/59.000",
    "说明": ""
  },
  {
    "住院流水号": "19072300000058",
    "记录时间": "2019-07-25 14:13:00",
    "检测项": "呼吸",
    "单位": "次/分",
    "检测值": "20.000",
    "说明": ""
  },
  {
    "住院流水号": "19072300000058",
    "记录时间": "2019-07-25 18:43:00",
    "检测项": "小便",
    "单位": "ml",
    "检测值": "2000.000",
    "说明": ""
  },
  {
    "住院流水号": "19072300000058",
    "记录时间": "2019-07-25 18:43:00",
    "检测项": "小便",
    "单位": "ml",
    "检测值": "100.000",
    "说明": ""
  },
  {
    "住院流水号": "19072300000058",
    "记录时间": "2019-07-25 18:48:00",
    "检测项": "脉搏",
    "单位": "次/分",
    "检测值": "78.000",
    "说明": ""
  },
  {
    "住院流水号": "19072300000058",
    "记录时间": "2019-07-25 18:48:00",
    "检测项": "体温",
    "单位": "℃",
    "检测值": "37.200",
    "说明": "耳温测量仪；"
  },
  {
    "住院流水号": "19072300000058",
    "记录时间": "2019-07-25 18:48:00",
    "检测项": "呼吸",
    "单位": "次/分",
    "检测值": "19.000",
    "说明": ""
  },
  {
    "住院流水号": "19072300000058",
    "记录时间": "2019-07-26 06:40:00",
    "检测项": "体温",
    "单位": "℃",
    "检测值": "36.700",
    "说明": "耳温测量仪；"
  },
  {
    "住院流水号": "19072300000058",
    "记录时间": "2019-07-26 06:40:00",
    "检测项": "血压",
    "单位": "mmHg",
    "检测值": "149.000/87.000",
    "说明": ""
  },
  {
    "住院流水号": "19072300000058",
    "记录时间": "2019-07-26 06:40:00",
    "检测项": "呼吸",
    "单位": "次/分",
    "检测值": "19.000",
    "说明": ""
  },
  {
    "住院流水号": "19072300000058",
    "记录时间": "2019-07-26 06:40:00",
    "检测项": "脉搏",
    "单位": "次/分",
    "检测值": "76.000",
    "说明": ""
  },
  {
    "住院流水号": "19072300000058",
    "记录时间": "2019-07-26 14:44:00",
    "检测项": "脉搏",
    "单位": "次/分",
    "检测值": "78.000",
    "说明": ""
  },
  {
    "住院流水号": "19072300000058",
    "记录时间": "2019-07-26 14:44:00",
    "检测项": "大便",
    "单位": "次",
    "检测值": "",
    "说明": ""
  },
  {
    "住院流水号": "19072300000058",
    "记录时间": "2019-07-26 14:44:00",
    "检测项": "体温",
    "单位": "℃",
    "检测值": "36.800",
    "说明": "耳温测量仪；"
  },
  {
    "住院流水号": "19072300000058",
    "记录时间": "2019-07-26 14:44:00",
    "检测项": "呼吸",
    "单位": "次/分",
    "检测值": "20.000",
    "说明": ""
  },
  {
    "住院流水号": "19072300000058",
    "记录时间": "2019-07-27 05:56:00",
    "检测项": "呼吸",
    "单位": "次/分",
    "检测值": "14.000",
    "说明": ""
  },
  {
    "住院流水号": "19072300000058",
    "记录时间": "2019-07-27 05:56:00",
    "检测项": "体温",
    "单位": "℃",
    "检测值": "36.900",
    "说明": "耳温测量仪；"
  },
  {
    "住院流水号": "19072300000058",
    "记录时间": "2019-07-27 05:56:00",
    "检测项": "脉搏",
    "单位": "次/分",
    "检测值": "72.000",
    "说明": ""
  }
]