[
  {
    "住院流水号": "20120400000258",
    "记录时间": "2020-12-04 13:29:00",
    "检测项": "体温",
    "单位": "℃",
    "检测值": "36.800",
    "说明": "耳温测量仪；"
  },
  {
    "住院流水号": "20120400000258",
    "记录时间": "2020-12-04 13:29:00",
    "检测项": "脉搏",
    "单位": "次/分",
    "检测值": "100.000",
    "说明": ""
  },
  {
    "住院流水号": "20120400000258",
    "记录时间": "2020-12-04 13:29:00",
    "检测项": "血压",
    "单位": "mmHg",
    "检测值": "109.000/74.000",
    "说明": ""
  },
  {
    "住院流水号": "20120400000258",
    "记录时间": "2020-12-04 13:29:00",
    "检测项": "身高",
    "单位": "cm",
    "检测值": "145.000",
    "说明": ""
  },
  {
    "住院流水号": "20120400000258",
    "记录时间": "2020-12-04 13:29:00",
    "检测项": "呼吸",
    "单位": "次/分",
    "检测值": "20.000",
    "说明": ""
  },
  {
    "住院流水号": "20120400000258",
    "记录时间": "2020-12-04 14:10:00",
    "检测项": "大便",
    "单位": "次",
    "检测值": "1.000",
    "说明": ""
  },
  {
    "住院流水号": "20120400000258",
    "记录时间": "2020-12-04 14:10:00",
    "检测项": "呼吸",
    "单位": "次/分",
    "检测值": "16.000",
    "说明": ""
  },
  {
    "住院流水号": "20120400000258",
    "记录时间": "2020-12-04 14:10:00",
    "检测项": "体温",
    "单位": "℃",
    "检测值": "36.700",
    "说明": "耳温测量仪；"
  },
  {
    "住院流水号": "20120400000258",
    "记录时间": "2020-12-04 14:10:00",
    "检测项": "脉搏",
    "单位": "次/分",
    "检测值": "76.000",
    "说明": ""
  },
  {
    "住院流水号": "20120400000258",
    "记录时间": "2020-12-04 14:36:00",
    "检测项": "脉搏",
    "单位": "次/分",
    "检测值": "110.000",
    "说明": ""
  },
  {
    "住院流水号": "20120400000258",
    "记录时间": "2020-12-04 14:36:00",
    "检测项": "呼吸",
    "单位": "次/分",
    "检测值": "24.000",
    "说明": ""
  },
  {
    "住院流水号": "20120400000258",
    "记录时间": "2020-12-04 15:12:00",
    "检测项": "体温",
    "单位": "℃",
    "检测值": "39.000/38.600",
    "说明": "耳温测量仪；"
  },
  {
    "住院流水号": "20120400000258",
    "记录时间": "2020-12-04 18:05:00",
    "检测项": "呼吸",
    "单位": "次/分",
    "检测值": "22.000",
    "说明": ""
  },
  {
    "住院流水号": "20120400000258",
    "记录时间": "2020-12-04 18:05:00",
    "检测项": "体温",
    "单位": "℃",
    "检测值": "37.400",
    "说明": "耳温测量仪；"
  },
  {
    "住院流水号": "20120400000258",
    "记录时间": "2020-12-04 18:05:00",
    "检测项": "脉搏",
    "单位": "次/分",
    "检测值": "92.000",
    "说明": ""
  },
  {
    "住院流水号": "20120400000258",
    "记录时间": "2020-12-04 21:29:00",
    "检测项": "脉搏",
    "单位": "次/分",
    "检测值": "116.000",
    "说明": ""
  },
  {
    "住院流水号": "20120400000258",
    "记录时间": "2020-12-04 21:29:00",
    "检测项": "呼吸",
    "单位": "次/分",
    "检测值": "26.000",
    "说明": ""
  },
  {
    "住院流水号": "20120400000258",
    "记录时间": "2020-12-04 22:02:00",
    "检测项": "体温",
    "单位": "℃",
    "检测值": "38.200",
    "说明": "耳温测量仪；"
  },
  {
    "住院流水号": "20120400000258",
    "记录时间": "2020-12-04 22:02:00",
    "检测项": "呼吸",
    "单位": "次/分",
    "检测值": "22.000",
    "说明": ""
  },
  {
    "住院流水号": "20120400000258",
    "记录时间": "2020-12-04 22:02:00",
    "检测项": "脉搏",
    "单位": "次/分",
    "检测值": "99.000",
    "说明": ""
  },
  {
    "住院流水号": "20120400000258",
    "记录时间": "2020-12-04 22:02:00",
    "检测项": "体温",
    "单位": "℃",
    "检测值": "38.900/38.200",
    "说明": "耳温测量仪；"
  },
  {
    "住院流水号": "20120400000258",
    "记录时间": "2020-12-05 02:38:00",
    "检测项": "脉搏",
    "单位": "次/分",
    "检测值": "98.000",
    "说明": ""
  },
  {
    "住院流水号": "20120400000258",
    "记录时间": "2020-12-05 02:38:00",
    "检测项": "体温",
    "单位": "℃",
    "检测值": "36.800",
    "说明": "耳温测量仪；"
  },
  {
    "住院流水号": "20120400000258",
    "记录时间": "2020-12-05 02:38:00",
    "检测项": "呼吸",
    "单位": "次/分",
    "检测值": "20.000",
    "说明": ""
  },
  {
    "住院流水号": "20120400000258",
    "记录时间": "2020-12-05 04:28:00",
    "检测项": "呼吸",
    "单位": "次/分",
    "检测值": "24.000",
    "说明": ""
  },
  {
    "住院流水号": "20120400000258",
    "记录时间": "2020-12-05 04:29:00",
    "检测项": "体温",
    "单位": "℃",
    "检测值": "38.800/38.300",
    "说明": "耳温测量仪；"
  },
  {
    "住院流水号": "20120400000258",
    "记录时间": "2020-12-05 04:42:00",
    "检测项": "脉搏",
    "单位": "次/分",
    "检测值": "129.000",
    "说明": ""
  },
  {
    "住院流水号": "20120400000258",
    "记录时间": "2020-12-05 06:37:00",
    "检测项": "脉搏",
    "单位": "次/分",
    "检测值": "99.000",
    "说明": ""
  },
  {
    "住院流水号": "20120400000258",
    "记录时间": "2020-12-05 06:37:00",
    "检测项": "呼吸",
    "单位": "次/分",
    "检测值": "20.000",
    "说明": ""
  },
  {
    "住院流水号": "20120400000258",
    "记录时间": "2020-12-05 06:37:00",
    "检测项": "体温",
    "单位": "℃",
    "检测值": "37.200",
    "说明": "耳温测量仪；"
  },
  {
    "住院流水号": "20120400000258",
    "记录时间": "2020-12-05 10:05:00",
    "检测项": "呼吸",
    "单位": "次/分",
    "检测值": "21.000",
    "说明": ""
  },
  {
    "住院流水号": "20120400000258",
    "记录时间": "2020-12-05 10:05:00",
    "检测项": "体温",
    "单位": "℃",
    "检测值": "36.700",
    "说明": "耳温测量仪；"
  },
  {
    "住院流水号": "20120400000258",
    "记录时间": "2020-12-05 10:10:00",
    "检测项": "心率",
    "单位": "次/分",
    "检测值": "113.000",
    "说明": ""
  },
  {
    "住院流水号": "20120400000258",
    "记录时间": "2020-12-05 14:09:00",
    "检测项": "大便",
    "单位": "次",
    "检测值": "1.000",
    "说明": ""
  },
  {
    "住院流水号": "20120400000258",
    "记录时间": "2020-12-05 14:09:00",
    "检测项": "心率",
    "单位": "次/分",
    "检测值": "121.000",
    "说明": ""
  },
  {
    "住院流水号": "20120400000258",
    "记录时间": "2020-12-05 14:09:00",
    "检测项": "呼吸",
    "单位": "次/分",
    "检测值": "26.000",
    "说明": ""
  },
  {
    "住院流水号": "20120400000258",
    "记录时间": "2020-12-05 14:46:00",
    "检测项": "体温",
    "单位": "℃",
    "检测值": "38.400/37.800",
    "说明": "耳温测量仪；"
  },
  {
    "住院流水号": "20120400000258",
    "记录时间": "2020-12-05 18:07:00",
    "检测项": "体温",
    "单位": "℃",
    "检测值": "37.200",
    "说明": "耳温测量仪；"
  },
  {
    "住院流水号": "20120400000258",
    "记录时间": "2020-12-05 18:11:00",
    "检测项": "呼吸",
    "单位": "次/分",
    "检测值": "25.000",
    "说明": ""
  },
  {
    "住院流水号": "20120400000258",
    "记录时间": "2020-12-05 18:11:00",
    "检测项": "心率",
    "单位": "次/分",
    "检测值": "104.000",
    "说明": ""
  },
  {
    "住院流水号": "20120400000258",
    "记录时间": "2020-12-06 02:03:00",
    "检测项": "体温",
    "单位": "℃",
    "检测值": "37.900",
    "说明": "耳温测量仪；"
  },
  {
    "住院流水号": "20120400000258",
    "记录时间": "2020-12-06 02:03:00",
    "检测项": "呼吸",
    "单位": "次/分",
    "检测值": "24.000",
    "说明": ""
  },
  {
    "住院流水号": "20120400000258",
    "记录时间": "2020-12-06 02:03:00",
    "检测项": "心率",
    "单位": "次/分",
    "检测值": "107.000",
    "说明": ""
  },
  {
    "住院流水号": "20120400000258",
    "记录时间": "2020-12-06 06:03:00",
    "检测项": "体温",
    "单位": "℃",
    "检测值": "37.200",
    "说明": "耳温测量仪；"
  },
  {
    "住院流水号": "20120400000258",
    "记录时间": "2020-12-06 06:03:00",
    "检测项": "呼吸",
    "单位": "次/分",
    "检测值": "30.000",
    "说明": ""
  },
  {
    "住院流水号": "20120400000258",
    "记录时间": "2020-12-06 06:04:00",
    "检测项": "心率",
    "单位": "次/分",
    "检测值": "100.000",
    "说明": ""
  },
  {
    "住院流水号": "20120400000258",
    "记录时间": "2020-12-06 09:45:00",
    "检测项": "呼吸",
    "单位": "次/分",
    "检测值": "24.000",
    "说明": ""
  },
  {
    "住院流水号": "20120400000258",
    "记录时间": "2020-12-06 09:45:00",
    "检测项": "体温",
    "单位": "℃",
    "检测值": "36.900",
    "说明": "耳温测量仪；"
  },
  {
    "住院流水号": "20120400000258",
    "记录时间": "2020-12-06 09:45:00",
    "检测项": "脉搏",
    "单位": "次/分",
    "检测值": "100.000",
    "说明": ""
  },
  {
    "住院流水号": "20120400000258",
    "记录时间": "2020-12-06 14:04:00",
    "检测项": "体温",
    "单位": "℃",
    "检测值": "37.300",
    "说明": "耳温测量仪；"
  },
  {
    "住院流水号": "20120400000258",
    "记录时间": "2020-12-06 14:04:00",
    "检测项": "脉搏",
    "单位": "次/分",
    "检测值": "98.000",
    "说明": ""
  },
  {
    "住院流水号": "20120400000258",
    "记录时间": "2020-12-06 14:04:00",
    "检测项": "呼吸",
    "单位": "次/分",
    "检测值": "18.000",
    "说明": ""
  },
  {
    "住院流水号": "20120400000258",
    "记录时间": "2020-12-06 14:04:00",
    "检测项": "大便",
    "单位": "次",
    "检测值": "",
    "说明": ""
  },
  {
    "住院流水号": "20120400000258",
    "记录时间": "2020-12-06 18:04:00",
    "检测项": "体温",
    "单位": "℃",
    "检测值": "37.700",
    "说明": "耳温测量仪；"
  },
  {
    "住院流水号": "20120400000258",
    "记录时间": "2020-12-06 18:04:00",
    "检测项": "呼吸",
    "单位": "次/分",
    "检测值": "22.000",
    "说明": ""
  },
  {
    "住院流水号": "20120400000258",
    "记录时间": "2020-12-06 18:04:00",
    "检测项": "脉搏",
    "单位": "次/分",
    "检测值": "98.000",
    "说明": ""
  },
  {
    "住院流水号": "20120400000258",
    "记录时间": "2020-12-07 06:13:00",
    "检测项": "呼吸",
    "单位": "次/分",
    "检测值": "19.000",
    "说明": ""
  },
  {
    "住院流水号": "20120400000258",
    "记录时间": "2020-12-07 06:13:00",
    "检测项": "脉搏",
    "单位": "次/分",
    "检测值": "82.000",
    "说明": ""
  },
  {
    "住院流水号": "20120400000258",
    "记录时间": "2020-12-07 06:13:00",
    "检测项": "体温",
    "单位": "℃",
    "检测值": "36.700",
    "说明": "耳温测量仪；"
  },
  {
    "住院流水号": "20120400000258",
    "记录时间": "2020-12-07 14:22:00",
    "检测项": "呼吸",
    "单位": "次/分",
    "检测值": "20.000",
    "说明": ""
  },
  {
    "住院流水号": "20120400000258",
    "记录时间": "2020-12-07 14:22:00",
    "检测项": "大便",
    "单位": "次",
    "检测值": "1.000",
    "说明": ""
  },
  {
    "住院流水号": "20120400000258",
    "记录时间": "2020-12-07 14:22:00",
    "检测项": "脉搏",
    "单位": "次/分",
    "检测值": "94.000",
    "说明": ""
  },
  {
    "住院流水号": "20120400000258",
    "记录时间": "2020-12-07 14:22:00",
    "检测项": "体温",
    "单位": "℃",
    "检测值": "36.900",
    "说明": "耳温测量仪；"
  },
  {
    "住院流水号": "20120400000258",
    "记录时间": "2020-12-07 18:13:00",
    "检测项": "脉搏",
    "单位": "次/分",
    "检测值": "99.000",
    "说明": ""
  },
  {
    "住院流水号": "20120400000258",
    "记录时间": "2020-12-07 18:13:00",
    "检测项": "呼吸",
    "单位": "次/分",
    "检测值": "20.000",
    "说明": ""
  },
  {
    "住院流水号": "20120400000258",
    "记录时间": "2020-12-07 18:13:00",
    "检测项": "体温",
    "单位": "℃",
    "检测值": "36.700",
    "说明": "耳温测量仪；"
  },
  {
    "住院流水号": "20120400000258",
    "记录时间": "2020-12-08 06:09:00",
    "检测项": "脉搏",
    "单位": "次/分",
    "检测值": "88.000",
    "说明": ""
  },
  {
    "住院流水号": "20120400000258",
    "记录时间": "2020-12-08 06:09:00",
    "检测项": "体温",
    "单位": "℃",
    "检测值": "36.700",
    "说明": "耳温测量仪；"
  },
  {
    "住院流水号": "20120400000258",
    "记录时间": "2020-12-08 06:09:00",
    "检测项": "呼吸",
    "单位": "次/分",
    "检测值": "20.000",
    "说明": ""
  },
  {
    "住院流水号": "20120400000258",
    "记录时间": "2020-12-08 13:52:00",
    "检测项": "体温",
    "单位": "℃",
    "检测值": "36.200",
    "说明": "耳温测量仪；"
  },
  {
    "住院流水号": "20120400000258",
    "记录时间": "2020-12-08 13:52:00",
    "检测项": "脉搏",
    "单位": "次/分",
    "检测值": "110.000",
    "说明": ""
  },
  {
    "住院流水号": "20120400000258",
    "记录时间": "2020-12-08 13:52:00",
    "检测项": "呼吸",
    "单位": "次/分",
    "检测值": "20.000",
    "说明": ""
  },
  {
    "住院流水号": "20120400000258",
    "记录时间": "2020-12-08 13:52:00",
    "检测项": "大便",
    "单位": "次",
    "检测值": "2.000",
    "说明": ""
  },
  {
    "住院流水号": "20120400000258",
    "记录时间": "2020-12-09 06:08:00",
    "检测项": "脉搏",
    "单位": "次/分",
    "检测值": "92.000",
    "说明": ""
  },
  {
    "住院流水号": "20120400000258",
    "记录时间": "2020-12-09 06:08:00",
    "检测项": "体温",
    "单位": "℃",
    "检测值": "36.700",
    "说明": "耳温测量仪；"
  },
  {
    "住院流水号": "20120400000258",
    "记录时间": "2020-12-09 06:08:00",
    "检测项": "呼吸",
    "单位": "次/分",
    "检测值": "19.000",
    "说明": ""
  },
  {
    "住院流水号": "20120400000258",
    "记录时间": "2020-12-09 15:01:00",
    "检测项": "脉搏",
    "单位": "次/分",
    "检测值": "94.000",
    "说明": ""
  },
  {
    "住院流水号": "20120400000258",
    "记录时间": "2020-12-09 15:01:00",
    "检测项": "大便",
    "单位": "次",
    "检测值": "1.000",
    "说明": ""
  },
  {
    "住院流水号": "20120400000258",
    "记录时间": "2020-12-09 15:01:00",
    "检测项": "体温",
    "单位": "℃",
    "检测值": "36.500",
    "说明": "耳温测量仪；"
  },
  {
    "住院流水号": "20120400000258",
    "记录时间": "2020-12-09 15:01:00",
    "检测项": "呼吸",
    "单位": "次/分",
    "检测值": "20.000",
    "说明": ""
  },
  {
    "住院流水号": "20120400000258",
    "记录时间": "2020-12-10 05:58:00",
    "检测项": "脉搏",
    "单位": "次/分",
    "检测值": "88.000",
    "说明": ""
  },
  {
    "住院流水号": "20120400000258",
    "记录时间": "2020-12-10 05:58:00",
    "检测项": "呼吸",
    "单位": "次/分",
    "检测值": "19.000",
    "说明": ""
  },
  {
    "住院流水号": "20120400000258",
    "记录时间": "2020-12-10 05:58:00",
    "检测项": "体温",
    "单位": "℃",
    "检测值": "36.400",
    "说明": "耳温测量仪；"
  },
  {
    "住院流水号": "20120400000258",
    "记录时间": "2020-12-10 08:45:00",
    "检测项": "血压",
    "单位": "mmHg",
    "检测值": "105.000/63.000",
    "说明": ""
  },
  {
    "住院流水号": "20120400000258",
    "记录时间": "2020-12-10 08:45:00",
    "检测项": "体重",
    "单位": "kg",
    "检测值": "47.600",
    "说明": ""
  },
  {
    "住院流水号": "20120400000258",
    "记录时间": "2020-12-10 08:56:00",
    "检测项": "体重",
    "单位": "kg",
    "检测值": "49.000",
    "说明": ""
  },
  {
    "住院流水号": "20120400000258",
    "记录时间": "2020-12-10 14:20:00",
    "检测项": "脉搏",
    "单位": "次/分",
    "检测值": "98.000",
    "说明": ""
  },
  {
    "住院流水号": "20120400000258",
    "记录时间": "2020-12-10 14:20:00",
    "检测项": "呼吸",
    "单位": "次/分",
    "检测值": "18.000",
    "说明": ""
  },
  {
    "住院流水号": "20120400000258",
    "记录时间": "2020-12-10 14:20:00",
    "检测项": "体温",
    "单位": "℃",
    "检测值": "36.600",
    "说明": "耳温测量仪；"
  },
  {
    "住院流水号": "20120400000258",
    "记录时间": "2020-12-10 14:20:00",
    "检测项": "大便",
    "单位": "次",
    "检测值": "1.000",
    "说明": ""
  },
  {
    "住院流水号": "20120400000258",
    "记录时间": "2020-12-11 06:04:00",
    "检测项": "脉搏",
    "单位": "次/分",
    "检测值": "92.000",
    "说明": ""
  },
  {
    "住院流水号": "20120400000258",
    "记录时间": "2020-12-11 06:04:00",
    "检测项": "呼吸",
    "单位": "次/分",
    "检测值": "21.000",
    "说明": ""
  },
  {
    "住院流水号": "20120400000258",
    "记录时间": "2020-12-11 06:04:00",
    "检测项": "体温",
    "单位": "℃",
    "检测值": "36.600",
    "说明": "耳温测量仪；"
  },
  {
    "住院流水号": "20120400000258",
    "记录时间": "2020-12-11 14:20:00",
    "检测项": "体温",
    "单位": "℃",
    "检测值": "36.600",
    "说明": "耳温测量仪；"
  },
  {
    "住院流水号": "20120400000258",
    "记录时间": "2020-12-11 14:20:00",
    "检测项": "大便",
    "单位": "次",
    "检测值": "1.000",
    "说明": ""
  },
  {
    "住院流水号": "20120400000258",
    "记录时间": "2020-12-11 14:20:00",
    "检测项": "脉搏",
    "单位": "次/分",
    "检测值": "89.000",
    "说明": ""
  },
  {
    "住院流水号": "20120400000258",
    "记录时间": "2020-12-11 14:20:00",
    "检测项": "呼吸",
    "单位": "次/分",
    "检测值": "18.000",
    "说明": ""
  },
  {
    "住院流水号": "20120400000258",
    "记录时间": "2020-12-12 05:52:00",
    "检测项": "脉搏",
    "单位": "次/分",
    "检测值": "86.000",
    "说明": ""
  },
  {
    "住院流水号": "20120400000258",
    "记录时间": "2020-12-12 05:52:00",
    "检测项": "呼吸",
    "单位": "次/分",
    "检测值": "19.000",
    "说明": ""
  },
  {
    "住院流水号": "20120400000258",
    "记录时间": "2020-12-12 05:52:00",
    "检测项": "体温",
    "单位": "℃",
    "检测值": "36.800",
    "说明": "耳温测量仪；"
  },
  {
    "住院流水号": "20120400000258",
    "记录时间": "2020-12-12 14:01:00",
    "检测项": "脉搏",
    "单位": "次/分",
    "检测值": "88.000",
    "说明": ""
  },
  {
    "住院流水号": "20120400000258",
    "记录时间": "2020-12-12 14:01:00",
    "检测项": "体温",
    "单位": "℃",
    "检测值": "36.200",
    "说明": "耳温测量仪；"
  },
  {
    "住院流水号": "20120400000258",
    "记录时间": "2020-12-12 14:01:00",
    "检测项": "大便",
    "单位": "次",
    "检测值": "1.000",
    "说明": ""
  },
  {
    "住院流水号": "20120400000258",
    "记录时间": "2020-12-12 14:01:00",
    "检测项": "呼吸",
    "单位": "次/分",
    "检测值": "18.000",
    "说明": ""
  }
]