[
  {
    "住院流水号": "19092800000211",
    "ICD10编码": "K50.900",
    "诊断编号": "1.00",
    "诊断时间": "2019-09-28 00:00:00",
    "诊断名称": "克罗恩病",
    "诊断类型": "入院诊断",
    "院内诊断编码": "30001674"
  },
  {
    "住院流水号": "19092800000211",
    "ICD10编码": "K50.900",
    "诊断编号": "",
    "诊断时间": "2019-09-28 16:42:33.473000",
    "诊断名称": "克罗恩病",
    "诊断类型": "",
    "院内诊断编码": "30001674"
  },
  {
    "住院流水号": "19092800000211",
    "ICD10编码": "K50.900",
    "诊断编号": "1.00",
    "诊断时间": "2019-09-30 00:00:00",
    "诊断名称": "克罗恩病",
    "诊断类型": "出院诊断",
    "院内诊断编码": "30001674"
  }
]